CHANGELOG.rst
MANIFEST.in
README.rst
setup.py
project_demo/manage.py
project_demo/demo/__init__.py
project_demo/demo/common.py
project_demo/demo/config.py
project_demo/demo/convert.py
project_demo/demo/urls.py
project_demo/demo/views.py
project_demo/project/__init__.py
project_demo/project/settings.py
project_demo/project/urls.py
project_demo/project/wsgi.py
test_service/__init__.py
test_service/conf.py
test_service/conf_no_settings.py
test_service/converge.py
test_service/curl_builder.py
test_service/curl_reader.py
test_service/debugger.py
test_service/json_encoder.py
test_service.egg-info/PKG-INFO
test_service.egg-info/SOURCES.txt
test_service.egg-info/dependency_links.txt
test_service.egg-info/requires.txt
test_service.egg-info/top_level.txt
test_service.egg-info/zip-safe
test_service/management/__init__.py
test_service/management/commands/__init__.py
test_service/management/commands/converge.py
test_service/management/commands/distinctcurl.py
test_service/management/commands/executecurl.py