Metadata-Version: 1.1
Name: test-service
Version: 1.2
Summary: test-service is a Python package that test web service base on linux curl.
Home-page: https://bitbucket.org/kylinfish/test-service
Author: kylinfish
Author-email: kylinfish@126.com
License: MIT License
Keywords: test-service
Platform: any
Classifier: Development Status :: 4 - Beta
Classifier: Environment :: Console
Classifier: Environment :: Web Environment
Classifier: Intended Audience :: Developers
Classifier: Programming Language :: Python
Classifier: Programming Language :: Python :: 2
Classifier: Programming Language :: Python :: 3
Classifier: Programming Language :: Python :: 3.4
Classifier: Topic :: Internet :: WWW/HTTP
Classifier: Topic :: Utilities
Classifier: Topic :: Software Development :: Libraries :: Python Modules
Classifier: License :: OSI Approved :: MIT License
